MANIFEST.in
pyproject.toml
pytest.ini
setup.cfg
src/CleanEmonBackend/__init__.py
src/CleanEmonBackend/__main__.py
src/CleanEmonBackend/API/API.py
src/CleanEmonBackend/API/__init__.py
src/CleanEmonBackend/API/app_factory.py
src/CleanEmonBackend/API/service.py
src/CleanEmonBackend/Disaggregator/__init__.py
src/CleanEmonBackend/Disaggregator/inference.py
src/CleanEmonBackend/Disaggregator/preparation.py
src/CleanEmonBackend/Disaggregator/service.py
src/CleanEmonBackend/lib/DBConnector.py
src/CleanEmonBackend/lib/__init__.py
src/CleanEmonBackend/lib/black_sorcery.py
src/CleanEmonBackend/lib/exceptions.py
src/CleanEmonBackend/lib/plots.py
src/CleanEmonBackend/lib/validation.py
src/CleanEmonBackend/scripts/__init__.py
src/CleanEmonBackend/scripts/disaggregate.py
src/CleanEmonBackend/scripts/setup.py
src/CleanEmonBackend/tests/__init__.py
src/CleanEmonBackend/tests/test_API/__init__.py
src/CleanEmonBackend/tests/test_API/test_API.py
src/CleanEmonBackend/tests/test_Disaggregator/__init__.py
src/CleanEmonBackend/tests/test_Disaggregator/conftest.py
src/CleanEmonBackend/tests/test_Disaggregator/energy_data.json
src/CleanEmonBackend/tests/test_Disaggregator/test_inference.py
src/CleanEmonBackend/tests/test_Disaggregator/test_preparation.py
src/CleanEmonBackend/tests/test_Disaggregator/test_service.py
src/CleanEmonBackend/tests/test_lib/2022-05-15.json
src/CleanEmonBackend/tests/test_lib/__init__.py
src/CleanEmonBackend/tests/test_lib/test_DBConnector.py
src/CleanEmonBackend/tests/test_lib/test_black_sorcery.py
src/CleanEmonBackend/tests/test_lib/test_plots.py
src/CleanEmonBackend/tests/test_lib/test_validation.py
src/CleanEmon_Backend.egg-info/PKG-INFO
src/CleanEmon_Backend.egg-info/SOURCES.txt
src/CleanEmon_Backend.egg-info/dependency_links.txt
src/CleanEmon_Backend.egg-info/requires.txt
src/CleanEmon_Backend.egg-info/top_level.txt