Metadata-Version: 2.1
Name: CleanEmon-Backend
Version: 0.5
Summary: A package providing all server-side artifacts of CleanEmon ecosystem
Author: George Vasiliadis
Author-email: geor.vasiliadis@gmail.com
Requires-Python: >=3.6
